fasthtmx/__init__.py
fasthtmx/headers.py
fasthtmx/router.py
fasthtmx/utils.py
fasthtmx-0.1.2.dist-info/METADATA
fasthtmx-0.1.2.dist-info/WHEEL
fasthtmx-0.1.2.dist-info/RECORD
