Metadata-Version: 2.1
Name: fasthtmx
Version: 0.1.2
Summary: 
Author: henrique
Author-email: henrique@xonha.space
Requires-Python: >=3.8,<4.0
Classifier: Programming Language :: Python :: 3
Classifier: Programming Language :: Python :: 3.8
Classifier: Programming Language :: Python :: 3.9
Classifier: Programming Language :: Python :: 3.10
Classifier: Programming Language :: Python :: 3.11
Classifier: Programming Language :: Python :: 3.12
Requires-Dist: fastapi (>=0.109.0,<0.110.0)
